elucidate/__init__.py
elucidate/elucidate.py
elucidate/exceptions.py
elucidate/monkeystrapper.py
elucidate/version.py
elucidate/evaluators/__init__.py
elucidate/evaluators/anthropic_evaluator.py
elucidate/evaluators/gemini_evaluator.py
elucidate/evaluators/openai_evaluator.py
elucidate/protocols/anthropic_service_protocol.py
elucidate/protocols/gemini_service_protocol.py
elucidate/protocols/openai_service_protocol.py
elucidate/util/attributes.py
elucidate/util/classes.py
elucidate/util/imports/easytl_importer.py
elucidate/util/llm_helper/curators.py
elucidate/util/llm_helper/validators.py
elucidate-0.0.3.1.dist-info/LICENSE.md
elucidate-0.0.3.1.dist-info/METADATA
elucidate-0.0.3.1.dist-info/WHEEL
elucidate-0.0.3.1.dist-info/top_level.txt
elucidate-0.0.3.1.dist-info/RECORD
